setup.cfg
setup.py
liscraper/__init__.py
liscraper/scraper.py
liscraper/spider.py
liscraper.egg-info/PKG-INFO
liscraper.egg-info/SOURCES.txt
liscraper.egg-info/dependency_links.txt
liscraper.egg-info/entry_points.txt
liscraper.egg-info/requires.txt
liscraper.egg-info/top_level.txt