Metadata-Version: 1.0
Name: liscraper
Version: 0.2.3
Summary: LinkedIn search people result scraper
Home-page: https://github.com/czekan/liscraper
Author: Tomasz Czekanski
Author-email: t.czekanski@gmail.com
License: GPL
Keywords: linkedin,scraper
Platform: UNKNOWN
